python_utilz/__init__.py
python_utilz/bytes_related.py
python_utilz/py.typed
python_utilz/strings_related.py
python_utilz/time_related.py
python_utilz/tests/__init__.py
python_utilz/tests/test_bytes_related.py
python_utilz/tests/test_strings_related.py
python_utilz/tests/test_time_related.py
python_utilz-0.1.6.dist-info/METADATA
python_utilz-0.1.6.dist-info/WHEEL
python_utilz-0.1.6.dist-info/licenses/LICENSE
python_utilz-0.1.6.dist-info/RECORD
