Metadata-Version: 2.4
Name: python-utilz
Version: 0.1.6
Summary: Set of handy python utilities
Author-email: Igor Zyktin <nicord@yandex.ru>
License-File: LICENSE
Requires-Python: >=3.10
